{
  "project_info": {
    "project_number": "171176283716",
    "project_id": "diabeteshealthmonitoringapp",
    "storage_bucket": "diabeteshealthmonitoringapp.appspot.com"
  },
  "client": [
    {
      "client_info": {
        "mobilesdk_app_id": "1:171176283716:android:4d5c1b9736341276797611",
        "android_client_info": {
          "package_name": "com.example.diabeteshealthmonitoringapplication"
        }
      },
      "oauth_client": [
        {
          "client_id": "171176283716-4uqgbq5q19v80oq5ud2eetaa03bj8p60.apps.googleusercontent.com",
          "client_type": 3
        }
      ],
      "api_key": [
        {
          "current_key": "AIzaSyBr5jfLEwo72HKXgtyQmHgDcKA3Jy0wckc"
        }
      ],
      "services": {
        "appinvite_service": {
          "other_platform_oauth_client": [
            {
              "client_id": "171176283716-4uqgbq5q19v80oq5ud2eetaa03bj8p60.apps.googleusercontent.com",
              "client_type": 3
            }
          ]
        }
      }
    }
  ],
  "configuration_version": "1"
}